uniprotparser/__init__.py
uniprotparser/betaparser.py
uniprotparser/cli.py
uniprotparser/parser.py
uniprotparser-1.2.1.dist-info/entry_points.txt
uniprotparser-1.2.1.dist-info/LICENSE.md
uniprotparser-1.2.1.dist-info/METADATA
uniprotparser-1.2.1.dist-info/WHEEL
uniprotparser-1.2.1.dist-info/RECORD
