Metadata-Version: 2.1
Name: uniprotparser
Version: 1.2.1
Summary: Getting Uniprot Data from Uniprot Accession ID through Uniprot REST API
Home-page: https://github.com/noatgnu/UniprotWebParser
License: MIT
Keywords: uniprot,protein sequence,database,parser
Author: Toan K. Phung
Author-email: toan.phungkhoiquoctoan@gmail.com
Requires-Python: >=3.9,<4.0
Classifier: License :: OSI Approved :: MIT License
Classifier: Programming Language :: Python :: 3
Classifier: Programming Language :: Python :: 3.9
Classifier: Programming Language :: Python :: 3.10
Classifier: Programming Language :: Python :: 3.11
Classifier: Programming Language :: Python :: 3.12
Requires-Dist: aiohttp (>=3.8.3,<4.0.0)
Requires-Dist: click (>=8.1.3,<9.0.0)
Requires-Dist: requests (>=2.28.2,<3.0.0)
Project-URL: Repository, https://github.com/noatgnu/UniprotWebParser
